{
    "name"  : "OpenTSDB",
    "production": true,
    "readonly": false,
    "queryParams": null,
    "debugLevel": "ERROR",
    "uiBranding": {
        "logo": {
            "imageUrl": "/assets/horizon-logo-icon-only.png",
            "homeUrl": "/main"
        }
    },
    "tsdbCacheMode": null,
    "tsdbSource": null,
    "tsdb_host": "<%tsdb endpoint%>",
    "tsdb_hosts": [
        "<%tsdb endpoint a%>",
        "<%tsdb endpoint b%>",
        "<%tsdb endpoint c%>"
    ],
    "webUI": "<% webui endpoint %>",
    "configdb": "<% configdb endpoint %>",
    "metaApi": "<% meta endpoint %>",
    "auraUI": "<% Aura UI endpoint %>",
    "alert": {
        "recipient": {
            "opsgenie": {
                "enable": false,
                "guideUrl": "<% opsgenie guide url %>"
        },
        "slack": {
            "enable": false,
            "guideUrl": "<% slack guide url %>"
        },
        "oc": {
            "enable": false,
            "onboardUrl": "<% OC onboard url %>",
            "guideUrl": "<% OC guide url %>"
        },
        "http": {
            "enable": false
        },
        "email": {
            "enable": true
        },
        "pagerduty": {
            "enable": false,
            "guideUrl": "<% pagerduty guide url %>"
        }
      }
    },
    "widget": {
        "downloadQuery": {
            "examples": [
                "<% query example 1 (curl?) %>",
                "<% query example 2 (CLI?) %>"
            ]
        }
    },
    "alert_history_url": "<% alert log history url %>",
    "helpLinks": [
        { "label": "User guide", "href": "#" },
        { "label": "File a ticket", "href": "#" },
        { "label": "Talk to us", "icon": "d-slack", "href": "#" }
    ],
    "modules": {
        "dashboard": {
            "widget": {
                "overrideTime": true
            }
        }
    },
    "namespace": {
        "enabled": false,
        "default": "_default"
    },
    "auth": {
        "loginURL": "/login",
        "heartbeatURL": "/heartbeat",
        "heartbeatImgURL": "/heartbeatimg",
        "heartbeatInterval": 600
    }
}

